<?xml version="1.0" encoding="UTF-8"?>
<DOCUMENT><P><TIME-ARG ID="0"><LINK EVENT_ARG="2" ID="15" TYPE_REL="EVENT_ARG"/><W> ১ </W><W> আষাঢ় </W><W> ১৪০৯ </W><W> রবিবার </W><W> ১৬ </W><W> জুন </W><W> ২০০২ </W></TIME-ARG></P><P><W> সংক্ষেপে.. </W><W> বিশাল </W><W> খোলা </W><W> নিয়ে </W><W> অনিশ্চয়তা </W><W> নিজস্ব </W><W> সংবাদদাতা </W><W> কলকাতা </W><W> বিশাল </W><W> ফ্যাশন </W><W> প্রাইভেট </W><W> লিমিটেডের </W><W> হাওড়ার </W><W> কারখানা </W><W> খোলা </W><W> নিয়ে </W><W> শ্রমিক </W><W> ও </W><W> মালিকপক্ষ </W><W> শনিবারেও </W><W> নিজেদের </W><W> অবস্থানে </W><W> অনড় </W><W> থাকায় </W><W> জটিলতা </W><W> কাটার </W><W> কোনও </W><W> সম্ভাবনা </W><W> আপাতত </W><W> দেখা </W><W> যাচ্ছে </W><W> না। </W></P><P><W> সিটুর </W><W> রাজ্য </W><W> সম্পাদক </W><W> চিত্তব্রত </W><W> মজুমদার </W><W> কারখানা </W><W> খোলার </W><W> প্রসঙ্গে </W><W> এ </W><W> দিন </W><W> বলেন, </W><W> ‘‘যাঁদের </W><W> নামে </W><W> থানায় </W><W> কোনও </W><W> দিন </W><W> কোনও </W><W> অভিযোগ </W><W> নেই, </W><W> মালিকপক্ষ </W><W> তাঁদেরও </W><W> হামলা </W><W> চালানোর </W><W> দোহাই </W><W> দিয়ে </W><W> ছাঁটাই </W><W> করতে </W><W> চাইছেন। </W><W> ওঁরা </W><W> আসলে </W><W> ইউনিয়নটাকেই </W><W> তুলে </W><W> দেওয়ার </W><W> চক্রান্ত </W><W> করছেন। </W><W> আমার </W><W> কাছে </W><W> খবর </W><W> আছে, </W><W> মালিকের </W><W> লোকজন </W><W> কারখানার </W><W> এক </W><W> দল </W><W> শ্রমিককে </W><W> হাত </W><W> করে </W><W> নিজেদের </W><W> পক্ষে </W><W> কাজে </W><W> লাগাচ্ছে।’’ </W><W> এ </W><W> দিকে, </W><W> সংস্থার </W><W> ডিরেক্টর </W><W> রামচন্দ্র </W><W> অগ্রবালও </W><W> তাঁর </W><W> বক্তব্যে </W><W> অনড়। </W><W> তাঁর </W><W> কথায়, </W><W> ‘‘হামলা </W><W> না </W><W> হলে </W><W> আমি </W><W> বলব </W><W> কেন? </W><W> আমি </W><W> আবারও </W><W> বলছি, </W><W> যে </W><W> ৯ </W><W> জন </W><W> হামলা </W><W> করেছেন </W><W> আমি </W><W> তাঁদেরই </W><W> ছাঁটাই </W><W> করতে </W><W> চাইছি। </W><W> সিটু </W><W> তা </W><W> না </W><W> মানলে </W><W> কারখানা </W><W> বন্ধ </W><W> থাকবে।’’ </W><W> শনিবার </W><W> দুপুরে </W><W> কারখানার </W><W> সামনে </W><W> সিটুর </W><W> পক্ষ </W><W> থেকে </W><W> ‘গেট </W><W> মিটিং’ </W><W> ডাকা </W><W> হয়। </W></P><P><W> গোয়ালতোড়ে </W><W> অভিযুক্ত </W><W> গৃহকর্তা </W></P><P><W> নিজস্ব </W><W> সংবাদদাতা, </W><W> মেদিনীপুর: </W><W> গোয়ালতোড়ের </W><W> জামিরগোট </W><W> গ্রামে </W><W> গত </W><W> ৩১ </W><W> মে </W><W> একই </W><W> পরিবারের </W><W> তিনজনের </W><W> খুনের </W><W> ঘটনায় </W><W> জেলা </W><W> তৃণমূলের </W><W> পক্ষ </W><W> থেকে </W><W> গৃহকর্তা </W><W> সৃষ্টিধর </W><W> দেব </W><W> সিংহের </W><W> বিরুদ্ধে </W><W> অভিযোগ </W><W> দায়ের </W><W> করা </W><W> হয়েছে। </W><W> শনিবার </W><W> দলের </W><W> পক্ষ </W><W> থেকে </W><W> বলা </W><W> হয়, </W><W> অর্থের </W><W> লোভেই </W><W> এই </W><W> হত্যাকাণ্ড </W><W> ঘটানো </W><W> হয়েছে। </W><W> জানুয়ারি </W><W> মাসে </W><W> সৃষ্টিধরবাবু </W><W> স্ত্রীর </W><W> নামে </W><W> একটি </W><W> বিমা </W><W> করান। </W><W> এর </W><W> পর </W><W> মাস </W><W> দুয়েক </W><W> আগে </W><W> মোটা </W><W> টাকার </W><W> আরও </W><W> একটি </W><W> বিমা </W><W> করেন। </W><W> ওই </W><W> বিমা </W><W> কোম্পানির </W><W> কাছে </W><W> থেকে </W><W> ওই </W><W> সংক্রান্ত </W><W> কাগজের </W><W> ফটোকপিও </W><W> সাংবাদিকদের </W><W> দেওয়া </W><W> হয়। </W></P><P><W> ডুবে </W><W> মৃত্যু </W><W> বাবা-ছেলের </W></P><P><W> নিজস্ব </W><W> সংবাদদাতা, </W><W> চুঁচুড়া: </W><W> সিঙ্গুর </W><W> থানার </W><W> বুড়ো </W><W> শান্তিগ্রামে </W><W> শনিবার </W><W> দুপুরে </W><W> পুকুরে </W><W> ডুবে </W><W> বাবা </W><W> ও </W><W> ছেলের </W><W> মৃত্যু </W><W> হয়েছে। </W><W> পুলিশ </W><W> জানিয়েছে, </W><W> পুকুরে </W><W> চান </W><W> করতে </W><W> গিয়ে </W><W> ছেলে </W><W> বিজয় </W><W> (১৫) </W><W> তলিয়ে </W><W> যাচ্ছে </W><W> দেখে </W><W> বাবা </W><W> জহরলাল </W><W> সাউ </W><W> (৪০) </W><W> তাকে </W><W> বাঁচাতে </W><W> যান। </W><W> কিন্তু </W><W> ছেলের </W><W> সঙ্গে </W><W> তিনিও </W><W> মারা </W><W> যান। </W><W> তাঁদের </W><W> বাড়ি </W><W> ভদ্রেশ্বরের </W><W> তেলেনিপাড়ায়। </W><W> আত্মীয়ের </W><W> বিয়ের </W><W> জন্য </W><W> তাঁরা </W><W> সিঙ্গুরে </W><W> যান। </W></P><P><W> চান </W><W> করতে </W><W> গিয়ে </W><W> মৃত্যু </W></P><P><W> নিজস্ব </W><W> সংবাদদাতা, </W><W> কলকাতা: </W><W> লিলুয়া </W><W> থানার </W><W> ‘ও’ </W><W> রোডের </W><W> একটি </W><W> পুকুরে </W><W> শনিবার </W><W> সকালে </W><W> চান </W><W> করতে </W><W> গিয়ে </W><W> জলে </W><W> ডুবে </W><W> এক </W><W> স্কুল </W><W> ছাত্রের </W><W> মৃত্যু </W><W> হয়েছে। </W><W> পুলিশ </W><W> জানিয়েছে, </W><W> ছাত্রটির </W><W> নাম </W><W> অমিত </W><W> দেয়াশি </W><W> (১০)। </W><W> তার </W><W> বাড়ি </W><W> স্থানীয় </W><W> ‘কে’ </W><W> রোডে। </W><W> এ </W><W> দিন </W><W> সকাল </W><W> সাড়ে </W><W> এগারোটা </W><W> থেকে </W><W> তাকে </W><W> খুঁজে </W><W> পাওয়া </W><W> যাচ্ছিল </W><W> না। </W><W> বিকেলে </W><W> তার </W><W> মৃতদেহ </W><W> উদ্ধার </W><W> করা </W><W> হয়। </W></P><P><PARTICIPANT-ARG ID="1"><LINK EVENT_ARG="2" ID="16" TYPE_REL="EVENT_ARG"/><W> দুষ্কৃতীর </W></PARTICIPANT-ARG><MAN_MADE_EVENT ID="2" TYPE="SHOOT_OUT"><W> গুলি, </W></MAN_MADE_EVENT><CASUALTIES-ARG ID="3"><LINK EVENT_ARG="2" ID="17" TYPE_REL="EVENT_ARG"/><W> হত </W><W> ১ </W></CASUALTIES-ARG></P><P><W> স্টাফ </W><W> রিপোর্টার, </W><W> কলকাতা: </W><PLACE-ARG ID="4"><LINK EVENT_ARG="6" ID="18" TYPE_REL="EVENT_ARG"/><W> বারাসতের </W><W> ষণ্ডালিয়া </W><W> অঞ্চলে </W></PLACE-ARG><PARTICIPANT-ARG ID="5"><LINK EVENT_ARG="6" ID="19" TYPE_REL="EVENT_ARG"/><W> দুষ্কৃতীদের </W></PARTICIPANT-ARG><MAN_MADE_EVENT ID="6" TYPE="SHOOT_OUT"><EVENT-COREF-LINK EVENT_ID="2" ID="28" TYPE_REL="EVENT_COREF"/><W> গুলিতে </W></MAN_MADE_EVENT><CASUALTIES-ARG ID="7"><LINK EVENT_ARG="6" ID="20" TYPE_REL="EVENT_ARG"/><W> প্রাণ </W><W> হারিয়েছেন </W><W> এক </W><W> যুবক। </W></CASUALTIES-ARG><W> তাঁর </W><W> নাম </W><W> নুর </W><W> ইসলাম </W><W> (৩৫)। </W><MAN_MADE_EVENT ID="15" TYPE="SHOOT_OUT"><EVENT-COREF-LINK EVENT_ID="6" ID="17" TYPE_REL="EVENT_COREF"/><W> ঘটনাটি </W><W> ঘটেছে </W></MAN_MADE_EVENT><TIME-ARG ID="9"><W> শনিবার </W><W> রাত </W><W> ৯টা </W><W> নাগাদ। </W></TIME-ARG><W> প্রাক্তন </W><W> তৃণমূল </W><W> কংগ্রেস </W><W> কর্মী </W><W> নুর </W><W> সাইকেলে </W><W> চেপে </W><W> একটি </W><W> চায়ের </W><W> দোকানে </W><W> চা </W><W> খাচ্ছিলেন। </W><W> সেখানেই </W><CASUALTIES-ARG ID="10"><LINK EVENT_ARG="11" ID="22" TYPE_REL="EVENT_ARG"/><W> তাঁকে </W></CASUALTIES-ARG><MAN_MADE_EVENT ID="11" TYPE="SHOOT_OUT"><EVENT-COREF-LINK EVENT_ID="15" ID="16" TYPE_REL="EVENT_COREF"/><W> গুলি </W><W> করে </W></MAN_MADE_EVENT><PARTICIPANT-ARG ID="12"><LINK EVENT_ARG="11" ID="23" TYPE_REL="EVENT_ARG"/><W> দুষ্কৃতীরা। </W></PARTICIPANT-ARG><W> রক্তাক্ত </W><W> অবস্থায় </W><AFTER_EFFECTS-ARG ID="13"><LINK EVENT_ARG="11" ID="24" TYPE_REL="EVENT_ARG"/><W> তাঁকে </W><W> বারাসত </W><W> হাসপাতালে </W><W> নিয়ে </W><W> যাওয়া </W><W> হয়। </W></AFTER_EFFECTS-ARG><CASUALTIES-ARG ID="14"><LINK EVENT_ARG="11" ID="25" TYPE_REL="EVENT_ARG"/><W> সেখানে </W><W> মারা </W><W> যান </W><W> তিনি। </W></CASUALTIES-ARG></P><P><W> রসগোল্লায় </W><W> বিষক্রিয়া </W></P><P><W> স্টাফ </W><W> রিপোর্টার, </W><W> বেলেঘাটা: </W><W> রসগোল্লা </W><W> খেয়ে </W><W> বিষক্রিয়ায় </W><W> অসুস্থ </W><W> হয়ে </W><W> বেলেঘাটার </W><W> আই </W><W> ডি </W><W> হাসপাতালে </W><W> ভর্তি </W><W> হয়েছেন </W><W> ১৪টি </W><W> শিশু-সহ </W><W> ১৬ </W><W> জন। </W><W> শনিবার </W><W> সকালে, </W><W> লেক </W><W> টাউনের </W><W> দক্ষিণদাড়িতে। </W><W> হাসপাতাল </W><W> সূত্রে </W><W> খবর, </W><W> দক্ষিণদাড়িতে </W><W> এক </W><W> ফেরিওয়ালা </W><W> এক </W><W> টাকায় </W><W> দশটি </W><W> রসগোল্লা </W><W> বিক্রি </W><W> করছিল। </W><W> অনেকেই </W><W> তা </W><W> কেনেন। </W><W> খাওয়ার </W><W> পরে </W><W> অনেকেরই </W><W> প্রচণ্ড </W><W> বমি </W><W> এবং </W><W> পেটের </W><W> গণ্ডগোল </W><W> শুরু </W><W> হয়। </W><W> হাসপাতালে </W><W> রোগীদের </W><W> চিকিৎসা </W><W> চলছে। </W></P></DOCUMENT>