<?xml version="1.0" encoding="UTF-8"?>
<DOCUMENT><P><NATURAL_EVENT ID="0" TYPE="CYCLONE"><W> ঘূর্ণিঝড় </W></NATURAL_EVENT><NAME-ARG ID="1"><LINK EVENT_ARG="0" ID="21" TYPE_REL="EVENT_ARG"/><W> ‘ফেথাই’র </W></NAME-ARG><W> প্রভাবে </W><W> আজও </W><W> বৃষ্টির </W><W> সম্ভাবনা </W></P><P><W> কালের </W><W> কণ্ঠ </W><W> অনলাইন </W><TIME-ARG ID="2"><LINK EVENT_ARG="0" ID="22" TYPE_REL="EVENT_ARG"/><W> ১৮ </W><W> ডিসেম্বর, </W><W> ২০১৮ </W><W> ০৯:৫৫ </W></TIME-ARG><W> শেয়ার </W><W> মন্তব্য()প্রিন্ট </W></P><P><NATURAL_EVENT ID="3" TYPE="CYCLONE"><EVENT-COREF-LINK EVENT_ID="0" ID="40" TYPE_REL="EVENT_COREF"/><W> ঘূর্ণিঝড় </W></NATURAL_EVENT><NAME-ARG ID="4"><LINK EVENT_ARG="3" ID="23" TYPE_REL="EVENT_ARG"/><W> ‘ফেথাই’র </W></NAME-ARG><W> প্রভাবে </W><W> আজও </W><W> বৃষ্টির </W><W> সম্ভাবনা </W></P><P><W> বঙ্গোপসাগরে </W><W> সৃষ্ট </W><NATURAL_EVENT ID="5" TYPE="CYCLONE"><EVENT-COREF-LINK EVENT_ID="3" ID="39" TYPE_REL="EVENT_COREF"/><W> ঘূর্ণিঝড় </W></NATURAL_EVENT><NAME-ARG ID="6"><LINK EVENT_ARG="5" ID="24" TYPE_REL="EVENT_ARG"/><W> ‘ফেথাই’ </W></NAME-ARG><W> এর </W><W> প্রভাবে </W><TIME-ARG ID="7"><LINK EVENT_ARG="5" ID="25" TYPE_REL="EVENT_ARG"/><W> গত </W><W> রবিবার </W><W> রাত </W><W> থেকে </W></TIME-ARG><W> বাংলাদেশের </W><W> আবহাওয়া </W><W> কিছুটা </W><W> বৈরী </W><W> হয়েছে। </W><W> এ </W><W> কারণে </W><TIME-ARG ID="8"><LINK EVENT_ARG="5" ID="26" TYPE_REL="EVENT_ARG"/><W> সোমবার </W><W> সকাল </W><W> থেকে </W></TIME-ARG><W> আকাশ </W><W> অনেকটাই </W><W> গোমড়া </W><W> ছিল। </W><W> সেই </W><W> সঙ্গে </W><AFTER_EFFECTS-ARG ID="9"><LINK EVENT_ARG="5" ID="27" TYPE_REL="EVENT_ARG"/><W> গুড়ি </W><W> গুড়ি </W><W> বৃষ্টিও </W></AFTER_EFFECTS-ARG><W> হয়েছে। </W><NATURAL_EVENT ID="10" TYPE="CYCLONE"><EVENT-COREF-LINK EVENT_ID="5" ID="38" TYPE_REL="EVENT_COREF"/><W> ঘূর্ণিঝড়টির </W></NATURAL_EVENT><W> প্রভাবে </W><W> এই </W><W> বৃষ্টি </W><W> আজও </W><W> হতে </W><W> পারে </W><W> বলে </W><W> জানিয়েছেন </W><W> আবহাওয়াবিদরা। </W><W> তাদের </W><W> মতে, </W><TIME-ARG ID="12"><LINK EVENT_ARG="10" ID="28" TYPE_REL="EVENT_ARG"/><W> পৌষের </W><W> প্রারম্ভের </W></TIME-ARG><W> এমন </W><W> বৃষ্টি </W><AFTER_EFFECTS-ARG ID="11"><LINK EVENT_ARG="10" ID="29" TYPE_REL="EVENT_ARG"/><W> জাকিয়ে </W><W> শীত </W><W> বয়ে </W><W> আনবে। </W></AFTER_EFFECTS-ARG></P><P><W> আবহাওয়াবিদ </W><W> মো. </W><W> ওমর </W><W> ফারুক </W><W> বলেন, </W><TIME-ARG ID="13"><LINK EVENT_ARG="14" ID="30" TYPE_REL="EVENT_ARG"/><W> সোমবার </W></TIME-ARG><W> ভারতে </W><W> আঘাত </W><W> হানার </W><W> আগে </W><NATURAL_EVENT ID="14" TYPE="CYCLONE"><EVENT-COREF-LINK EVENT_ID="10" ID="37" TYPE_REL="EVENT_COREF"/><W> ‘ফেথাই’ </W></NATURAL_EVENT><W> দুর্বল </W><W> হয়ে </W><W> যায়। </W><W> উপকূলে </W><W> আঘাত </W><W> হানার </W><W> সময় </W><W> গতিবেগ </W><W> ছিল </W><SPEED-ARG ID="15"><LINK EVENT_ARG="14" ID="31" TYPE_REL="EVENT_ARG"/><W> ঘণ্টায় </W><W> ৮০ </W><W> কিলোমিটার। </W></SPEED-ARG><W> দুর্বল </W><W> হলেও </W><NATURAL_EVENT ID="16" TYPE="CYCLONE"><EVENT-COREF-LINK EVENT_ID="14" ID="36" TYPE_REL="EVENT_COREF"/><W> এর </W></NATURAL_EVENT><W> প্রভাবে </W><PLACE-ARG ID="17"><LINK EVENT_ARG="16" ID="32" TYPE_REL="EVENT_ARG"/><W> দক্ষিণ </W><W> ভারতের </W><W> কয়েকটি </W><W> অঞ্চলে </W></PLACE-ARG><AFTER_EFFECTS-ARG ID="18"><LINK EVENT_ARG="16" ID="33" TYPE_REL="EVENT_ARG"/><W> প্রচুর </W><W> বৃষ্টি </W><W> হচ্ছে। </W></AFTER_EFFECTS-ARG><W> তার </W><W> প্রভাব </W><W> পড়েছে </W><W> বাংলাদেশেও। </W><NATURAL_EVENT ID="19" TYPE="CYCLONE"><EVENT-COREF-LINK EVENT_ID="16" ID="35" TYPE_REL="EVENT_COREF"/><W> ঘূর্ণিঝড়ের </W></NATURAL_EVENT><W> প্রভাবে </W><AFTER_EFFECTS-ARG ID="20"><LINK EVENT_ARG="19" ID="34" TYPE_REL="EVENT_ARG"/><W> বঙ্গোপসাগর </W><W> অনেকটাই </W><W> উত্তাল। </W></AFTER_EFFECTS-ARG><W> এ </W><W> কারণে </W><W> বাংলাদেশের </W><W> বিভিন্ন </W><W> সমুদ্রবন্দরকে </W><W> ২ </W><W> নম্বর </W><W> দূরবর্তী </W><W> হুশিয়ারি </W><W> সংকেত </W><W> দেখিয়ে </W><W> যেতে </W><W> বলা </W><W> হয়েছে। </W></P><P><W> আবহাওয়া </W><W> অফিস </W><W> জানিয়েছে, </W><W> প্রায় </W><W> সারা </W><W> দেশের </W><W> আকাশই </W><W> মেঘে </W><W> ঢাকা </W><W> থাকবে। </W><W> কোথাও </W><W> গুঁড়ি </W><W> গুঁড়ি </W><W> বৃষ্টি </W><W> হতে </W><W> পারে। </W><W> তবে </W><W> কাল </W><W> থেকে </W><W> পরিস্থিতির </W><W> উন্নতি </W><W> হয়ে </W><W> যাবে। </W></P><P><W> এদিকে </W><W> আবহাওয়া </W><W> অধিদফতরের </W><W> বিশেষ </W><W> বিজ্ঞপ্তিতে </W><W> উত্তর </W><W> বঙ্গোপসাগরে </W><W> অবস্থানরত </W><W> মাছ </W><W> ধরার </W><W> নৌকা </W><W> ও </W><W> ট্রলারগুলোকে </W><W> পরবর্তী </W><W> নির্দেশ </W><W> না </W><W> দেয়া </W><W> পর্যন্ত </W><W> উপকূলের </W><W> কাছাকাছি </W><W> থেকে </W><W> সাবধানে </W><W> চলাচল </W><W> করতে </W><W> বলা </W><W> হয়েছে। </W><W> সেই </W><W> সঙ্গে </W><W> তাদের </W><W> গভীর </W><W> সাগরে </W><W> বিচরণ </W><W> না </W><W> করতে </W><W> বলা </W><W> হয়েছে। </W></P></DOCUMENT>