<?xml version="1.0" encoding="UTF-8"?>
<DOCUMENT><DESC/><DESC/><DESC/><DESC/><DESC/><DESC/><TIME>9879</TIME><P><PLACE-ARG ID="0"><LINK EVENT_ARG="2" ID="22" TYPE_REL="EVENT_ARG"/><W> यूपी </W></PLACE-ARG><W> में </W><NATURAL_EVENT ID="2" TYPE="COLD_WAVE"><W> बर्फीली </W><W> सर्दी, </W></NATURAL_EVENT><W> इन </W><AFTER_EFFECTS-ARG ID="24"><LINK EVENT_ARG="2" ID="25" TYPE_REL="EVENT_ARG"/><W> ट्रेनों </W><W> के </W><W> हुए </W><W> चक्के </W><W> जाम </W></AFTER_EFFECTS-ARG></P><P><PLACE-ARG ID="1"><LINK EVENT_ARG="3" ID="26" TYPE_REL="EVENT_ARG"/><W> राजधानी </W></PLACE-ARG><W> में </W><TIME-ARG ID="5"><LINK EVENT_ARG="3" ID="27" TYPE_REL="EVENT_ARG"/><W> रविवार </W></TIME-ARG><W> को </W><W> दिन </W><W> भर </W><NATURAL_EVENT ID="3" TYPE="COLD_WAVE"><EVENT-COREF-LINK EVENT_ID="2" ID="58" TYPE_REL="EVENT_COREF"/><W> बर्फीली </W><W> हवा </W></NATURAL_EVENT><W> बहने </W><W> और </W><W> गलन </W><W> ने </W><AFTER_EFFECTS-ARG ID="6"><LINK EVENT_ARG="3" ID="28" TYPE_REL="EVENT_ARG"/><W> जनजीवन </W><W> बुरी </W><W> तरह </W><W> प्रभावित </W></AFTER_EFFECTS-ARG><W> रहा। </W><AFTER_EFFECTS-ARG ID="7"><LINK EVENT_ARG="3" ID="29" TYPE_REL="EVENT_ARG"/><W> लोग </W><W> घरों </W><W> में </W><W> कैद </W><W> रहे </W></AFTER_EFFECTS-ARG><W> तो </W><AFTER_EFFECTS-ARG ID="10"><LINK EVENT_ARG="3" ID="30" TYPE_REL="EVENT_ARG"/><W> सड़कों </W><W> पर </W><W> भी </W><W> भीड़ </W><W> कम </W></AFTER_EFFECTS-ARG><W> दिखी। </W><W> सुबह </W><W> और </W><W> शाम </W><W> को </W><AFTER_EFFECTS-ARG ID="8"><LINK EVENT_ARG="3" ID="31" TYPE_REL="EVENT_ARG"/><W> जबर्दस्त </W><W> कोहरे </W></AFTER_EFFECTS-ARG><W> के </W><W> चलते </W><W> यातायात </W><W> पर </W><W> भी </W><W> असर </W><W> पड़ा। </W><W> दोपहर </W><W> बाद </W><W> करीब </W><W> डेढ़ </W><W> घंटे </W><W> के </W><W> लिए </W><W> धूप </W><W> तो </W><W> निकली, </W><W> लेकिन </W><W> सूरज </W><W> बेअसर </W><W> ही </W><W> रहा। </W><W> आलम </W><W> यह </W><W> रहा </W><W> कि </W><W> अभी </W><W> तक </W><W> जहां </W><W> शहर </W><W> के </W><W> लोग </W><W> न्यूनतम </W><W> तापमान </W><W> गिरने </W><W> से </W><W> ठिठुर </W><W> रहे </W><W> थे, </W><W> रविवार </W><W> को </W><W> अधिकतम </W><W> तापमान </W><W> 11 </W><W> डिग्री </W><W> सेल्सियस </W><W> से </W><W> ऊपर </W><W> नहीं </W><W> चढ़ </W><W> पाने </W><W> से </W><W> ठंड </W><W> से </W><W> कांपते </W><W> रहे। </W><AFTER_EFFECTS-ARG ID="13"><LINK EVENT_ARG="3" ID="32" TYPE_REL="EVENT_ARG"/><W> राजधानी </W><W> का </W><W> अधिकतम </W><W> तापमान </W><W> रविवार </W><W> को </W><W> सामान्य </W><W> से </W><W> 12 </W><W> डिग्री </W><W> कम </W><W> 11 </W><W> डिग्री </W><W> सेल्सियस </W><W> रिकार्ड </W><W> किया </W></AFTER_EFFECTS-ARG><W> गया। </W><W> जबकि </W><W> न्यूनतम </W><W> तापमान </W><W> 5.3 </W><W> डिग्री </W><W> सेल्सियस </W><W> दर्ज </W><W> हुआ। </W><W> ये </W><W> सामान्य </W><W> से </W><W> तीन </W><W> डिग्री </W><W> सेल्सियस </W><W> कम </W><W> था। </W><W> वहीं, </W><W> कोहरे </W><W> के </W><W> चलते </W><W> सुबह </W><W> 8 </W><W> बजे </W><W> तक </W><AFTER_EFFECTS-ARG ID="9"><LINK EVENT_ARG="3" ID="33" TYPE_REL="EVENT_ARG"/><W> बिजिबिलटी </W><W> 20 </W><W> मीटर </W></AFTER_EFFECTS-ARG><W> रही। </W><W> रविवार </W><W> होने </W><W> के </W><W> बावजूद </W><AFTER_EFFECTS-ARG ID="12"><LINK EVENT_ARG="3" ID="34" TYPE_REL="EVENT_ARG"/><W> शाम </W><W> के </W><W> बाद </W><W> बाजारों </W><W> में </W><W> चहल-पहल </W><W> बहुत </W><W> कम </W></AFTER_EFFECTS-ARG><W> रही। </W><W> रात </W><W> को </W><W> एक </W><W> बार </W><W> बर्फीली </W><W> हवा </W><W> ने </W><W> ठिठुराया। </W><W> शाम </W><W> पांच </W><W> बजते-बजते </W><W> को </W><W> कोहरे </W><W> के </W><W> कारण </W><W> अंधेरा </W><W> छाने </W><W> लगा </W><W> और </W><AFTER_EFFECTS-ARG ID="11"><LINK EVENT_ARG="3" ID="35" TYPE_REL="EVENT_ARG"/><W> शाम </W><W> 7:30 </W><W> बजे </W><W> तक </W><W> शहर </W><W> घने </W><W> कोहरे </W><W> की </W><W> चादर </W><W> में </W><W> लिपट </W></AFTER_EFFECTS-ARG><W> गया। </W></P><P><W> कोहरे </W><W> के </W><W> चलते </W><W> करीब </W><AFTER_EFFECTS-ARG ID="14"><LINK EVENT_ARG="3" ID="36" TYPE_REL="EVENT_ARG"/><W> 130 </W><W> ट्रेनों </W><W> का </W><W> संचालन </W><W> बुरी </W><W> तरह </W><W> प्रभावित </W></AFTER_EFFECTS-ARG><W> हुआ। </W><AFTER_EFFECTS-ARG ID="15"><LINK EVENT_ARG="3" ID="37" TYPE_REL="EVENT_ARG"/><W> उत्तर </W><W> और </W><W> पूर्वोत्तर </W><W> रेलवे </W><W> लखनऊ </W><W> मंडल </W><W> के </W><W> 313 </W><W> स्टेशन </W><W> भीषण </W><W> कोहरे </W><W> की </W><W> चपेट </W><W> में </W></AFTER_EFFECTS-ARG><W> बने </W><W> रहे। </W><W> नेशनल </W><W> ट्रेन </W><W> इंक्वायरी </W><W> सिस्टम </W><W> (एनटीईएस) </W><W> में </W><W> ट्रेनों </W><W> की </W><W> स्थिति </W><W> अपडेट </W><W> न </W><W> होने </W><W> के </W><W> कारण </W><W> यात्रियों </W><W> को </W><W> खासी </W><W> दिक्कतों </W><W> का </W><W> सामना </W><W> करना </W><W> पड़ा। </W><AFTER_EFFECTS-ARG ID="16"><LINK EVENT_ARG="3" ID="38" TYPE_REL="EVENT_ARG"/><W> रविवार </W><W> को </W><W> ट्रेन </W><W> 11123 </W><W> बरौनी </W><W> -ग्वालियर </W><W> मेल </W><W> बरौनी </W><W> से </W><W> रवाना </W><W> नहीं </W><W> हो </W><W> सकी </W><W> इस </W><W> वजह </W><W> से </W><W> ये </W><W> ट्रेन </W><W> सोमवार </W><W> को </W><W> लखनऊ </W><W> नहीं </W><W> आएगी। </W></AFTER_EFFECTS-ARG><AFTER_EFFECTS-ARG ID="17"><LINK EVENT_ARG="3" ID="39" TYPE_REL="EVENT_ARG"/><W> 12230 </W><W> लखनऊ </W><W> मेल </W><W> पांच </W><W> घंटे, </W><W> 14864 </W><W> मरुधर </W><W> एक्सप्रेस </W><W> 9 </W><W> घंटे, </W><W> 12556 </W><W> गोरखधाम </W><W> 7 </W><W> घंटे, </W><W> 14512 </W><W> नौचंडी </W><W> एक्सप्रेस </W><W> 7 </W><W> घंटे </W><W> देरी </W><W> से </W><W> चल </W><W> रही </W></AFTER_EFFECTS-ARG><W> हैं। </W><AFTER_EFFECTS-ARG ID="18"><LINK EVENT_ARG="3" ID="40" TYPE_REL="EVENT_ARG"/><W> 14004 </W><W> न्यू </W><W> फरख्‍खा </W><W> एक्सप्रेस </W><W> 4 </W><W> घंटे, </W><W> 15708 </W><W> आम्रपाली </W><W> 7.30 </W><W> घंटे </W><W> लेट </W></AFTER_EFFECTS-ARG><W> हो </W><W> चुकी </W><W> है।वहीं </W><AFTER_EFFECTS-ARG ID="19"><LINK EVENT_ARG="3" ID="41" TYPE_REL="EVENT_ARG"/><W> 12232 </W><W> चंडीगढ़- </W><W> लखनऊ </W><W> 15 </W><W> घंटे </W><W> ,12524 </W><W> नई </W><W> दिल्ली </W><W> जलपाईगुडी </W><W> एक्सप्रेस </W><W> 13 </W><W> घंटे,12238 </W><W> बेगमपुरा </W><W> 7 </W><W> घंटे,14674 </W><W> शहीद </W><W> एक्सप्रेस </W><W> 5 </W><W> घंटे </W><W> और13258 </W><W> जनसाधरण </W><W> 8.30 </W><W> घंटे </W><W> लेट </W></AFTER_EFFECTS-ARG><W> पहुंचेगी।12183 </W><AFTER_EFFECTS-ARG ID="20"><LINK EVENT_ARG="3" ID="42" TYPE_REL="EVENT_ARG"/><W> भोपाल </W><W> एक्सप्रेस </W><W> 4 </W><W> घंटे, </W><W> 12331 </W><W> हिमगिरी </W><W> एक्सप्रेस </W><W> 12 </W><W> घंटे, </W><W> 54251 </W><W> लखनऊ-सराहनपुर </W><W> पैसेंजर </W><W> 11 </W><W> घंटे, </W><W> 15909 </W><W> अवध </W><W> आसाम </W><W> 5 </W><W> घंटे,12203 </W><W> अमृतसर </W><W> गरीबरथ </W><W> 5.30 </W><W> घंटे, </W><W> 14257 </W><W> काशी </W><W> विश्वनाथ </W><W> 13.30 </W><W> घंटे </W><W> लेट </W></AFTER_EFFECTS-ARG><W> है। </W><AFTER_EFFECTS-ARG ID="21"><LINK EVENT_ARG="3" ID="43" TYPE_REL="EVENT_ARG"/><W> 14511 </W><W> नौचंडी </W><W> एक्सप्रेस </W><W> 10 </W><W> घंटे, </W><W> 14649 </W><W> सरयू </W><W> यमुना </W><W> 12 </W><W> घंटे </W><W> और </W><W> 13005 </W><W> पंजाब </W><W> मेल </W><W> 16 </W><W> घंटे </W><W> देरी </W><W> से </W><W> आएगी। </W></AFTER_EFFECTS-ARG></P><P><W> घने </W><W> कोहरे </W><W> की </W><W> वजह </W><W> से </W><AFTER_EFFECTS-ARG ID="44"><LINK EVENT_ARG="3" ID="52" TYPE_REL="EVENT_ARG"/><W> रेलवे </W><W> ने </W><W> अगले </W><W> डेढ़ </W><W> महीने </W><W> के </W><W> लिए </W><W> कुछ </W><W> ट्रेनों </W><W> को </W><W> निरस्त </W><W> कर </W><W> दिया </W></AFTER_EFFECTS-ARG><W> है। </W><W> ये </W><W> ट्रेनें </W><W> हैं- </W><W> 12369/ </W><W> 70 </W><W> हावड़ा-हरिद्वार </W><W> कुंभ </W><W> एक्सप्रेस, </W><W> 13119/ </W><W> 20 </W><W> सियालदाह-दिल्ली </W><W> एक्सप्रेस, </W><W> 13255/ </W><W> 56 </W><W> दानापुर-चंडीगढ़ </W><W> एक्सप्रेस,13257/ </W><W> 58 </W><W> राजेंद्र </W><W> नगर-आनंद </W><W> बिहार </W><W> जनसाधारण </W><W> और </W><W> 5483/84 </W><W> दिल्ली-अलीपुरद्वार </W><W> महानंदा </W><W> एक्सप्रेस।ट्रेन </W><W> 13131 </W><W> व </W><W> 32 </W><W> कोलकाता-आनंद </W><W> विहार </W><W> एक्सप्रेस </W><W> आगामी </W><W> 31 </W><W> दिसंबर </W><W> से </W><W> लेकर </W><W> 16 </W><W> फरवरी </W><W> के </W><W> मध्य </W><W> मुगलसराय </W><W> जंक्शन </W><W> से </W><W> आनंद </W><W> विहार </W><W> टर्मिनल </W><W> तक </W><W> नहीं </W><W> चलेगी।विमान </W><W> भी </W><W> हुए </W><W> प्रभावितकम </W><W> विजिबिल्टी </W><W> की </W><W> वजह </W><W> से </W><W> कई </W><W> विमान </W><W> जहां </W><W> कई-कई </W><W> घंटे </W><W> लेट </W><W> रहे। </W><W> वही </W><W> शून्य </W><W> दृश्यता </W><W> को </W><W> देखते </W><W> हुए </W><W> दोपहर </W><W> को </W><W> इंडिगो </W><W> एयरलांइस </W><W> की </W><W> दिल्ली </W><W> से </W><W> लखनऊ </W><W> व </W><W> वाया </W><W> दिल्ली </W><W> होते </W><W> हुए </W><W> श्रीनगर </W><W> जाने </W><W> वाली </W><W> तथा </W><W> शाम </W><W> को </W><W> अहमदाबाद </W><W> से </W><W> दिल्ली </W><W> होते </W><W> हुए </W><W> लखनऊ </W><W> और </W><W> वाया </W><W> दिल्ली </W><W> होकर </W><W> मुम्बई </W><W> जाने </W><W> वाली </W><W> चार </W><W> उडाने </W><W> 6ई-522, </W><W> 525, </W><W> 146 </W><W> और </W><W> 184 </W><W> रद्द </W><W> कर </W><W> दी </W><W> गई। </W><W> कोहरे </W><W> की </W><W> वजह </W><W> से </W><W> शनिवार </W><W> की </W><W> रात </W><W> 11:45 </W><W> बजे </W><AFTER_EFFECTS-ARG ID="45"><LINK EVENT_ARG="3" ID="53" TYPE_REL="EVENT_ARG"/><W> दुबई </W><W> से </W><W> अमौसी </W><W> एयरपोर्ट </W><W> आने </W><W> वाली </W><W> एयरइंडिया </W><W> एक्सप्रेस </W><W> उडान </W><W> करीब </W><W> 12 </W><W> घंटे </W><W> देरी </W><W> से </W><W> रविवार </W><W> की </W><W> दोपहर </W><W> 12:10 </W><W> बजे </W><W> पहुंच </W><W> सकी। </W></AFTER_EFFECTS-ARG><W> वही </W><AFTER_EFFECTS-ARG ID="46"><LINK EVENT_ARG="3" ID="54" TYPE_REL="EVENT_ARG"/><W> सुबह </W><W> के </W><W> समय </W><W> यहां </W><W> आने </W><W> वाली </W><W> एयर </W><W> इंडिया, </W><W> इंडिगो, </W><W> जेटएयरवेज </W><W> व </W><W> गो </W><W> एयर </W><W> के </W><W> विमान </W><W> भी </W><W> कई </W><W> घंटे </W><W> विलम्ब </W></AFTER_EFFECTS-ARG><W> रहे। </W><W> दोपहर </W><W> करीब </W><W> 12 </W><W> बजे </W><W> के </W><W> बाद </W><W> ही </W><W> इनका </W><W> संचालन </W><W> शुरू </W><W> हो </W><W> सका। </W></P><P><PLACE-ARG ID="47"><LINK EVENT_ARG="48" ID="55" TYPE_REL="EVENT_ARG"/><W> राजधानी </W></PLACE-ARG><W> में </W><NATURAL_EVENT ID="48" TYPE="COLD_WAVE"><EVENT-COREF-LINK EVENT_ID="2" ID="59" TYPE_REL="EVENT_COREF"/><W> शीत </W><W> लहर </W><W> और </W><W> भयंकर </W><W> सर्दी </W></NATURAL_EVENT><W> को </W><W> देखते </W><W> हुए </W><AFTER_EFFECTS-ARG ID="50"><LINK EVENT_ARG="48" ID="56" TYPE_REL="EVENT_ARG"/><W> जिला </W><W> प्रशासन </W><W> ने </W><W> नौवीं </W><W> से </W><W> कक्षा </W><W> 12 </W><W> के </W><W> भी </W><W> स्कूल </W><W> एक </W><W> जनवरी </W><W> तक </W><W> बंद </W><W> कर </W><W> दिए </W></AFTER_EFFECTS-ARG><W> हैं। </W><W> अभी </W><W> तक </W><W> केवल </W><W> कक्षा </W><W> आठ </W><W> तक </W><W> के </W><W> स्कूलों </W><W> के </W><W> लिए </W><W> ही </W><W> छुट्टी </W><W> घोषित </W><W> की </W><W> गई </W><W> थीं। </W><W> कक्षा </W><W> नौ </W><W> से </W><W> 12 </W><W> तक </W><W> के </W><W> स्कूल </W><W> सोमवार </W><W> से </W><W> सुबह </W><W> 10 </W><W> बजे </W><W> से </W><W> दोपहर </W><W> दो </W><W> बजे </W><W> के </W><W> बीच </W><W> खुलने </W><W> थे।इस </W><W> बीच </W><W> रविवार </W><W> को </W><W> मौसम </W><W> के </W><W> बिगड़े </W><W> मिजाज </W><W> को </W><W> देखते </W><W> हुए </W><W> जिला </W><W> अधिकारी </W><W> राजशेखर </W><W> ने </W><W> 12वीं </W><W> तक </W><W> के </W><W> स्कूल </W><W> भी </W><W> बंद </W><W> करने </W><W> का </W><W> आदेश </W><W> जारी </W><W> कर </W><W> दिया।जिला </W><W> अधिकारी </W><W> के </W><W> अनुसार </W><W> कक्षा </W><W> 12 </W><W> तक </W><W> के </W><W> सभी </W><W> स्कूल </W><W> एक </W><W> जनवरी </W><W> तक </W><W> बंद </W><W> रहेंगे। </W><W> भले </W><W> ही </W><W> वो </W><W> किसी </W><W> बोर्ड </W><W> से </W><W> संबद्ध </W><W> हों।इस </W><W> समय </W><W> अगर </W><W> किसी </W><W> स्कूल </W><W> में </W><W> परीक्षा </W><W> या </W><W> कोई </W><W> दूसरा </W><W> जरूरी </W><W> इवेंट </W><W> हो </W><W> तो </W><W> उसे </W><W> आगे </W><W> के </W><W> लिए </W><W> स्थगित </W><W> कर </W><W> दिया </W><W> जाए। </W><W> अगर </W><W> कोई </W><W> ऐसा </W><W> इवेंट </W><W> है </W><W> जिसे </W><W> टाला </W><W> नहीं </W><W> जा </W><W> सकता </W><W> है </W><W> तो </W><W> उसके </W><W> लिए </W><W> जिला </W><W> अधिकारी </W><W> अनुमति </W><W> के </W><W> बाद </W><W> ही </W><W> स्कूल </W><W> खोला </W><W> जाएगा। </W><W> ऐसा </W><W> न </W><W> होने </W><W> पर </W><W> जिला </W><W> बेसिक </W><W> शिक्षा </W><W> अधिकारी, </W><W> डीआईओएस </W><W> और </W><W> सभी </W><W> थानाध्यक्षों </W><W> को </W><W> स्कूल </W><W> संचालकों </W><W> के </W><W> खिलाफ </W><W> कार्रवाई </W><W> करने </W><W> के </W><W> निर्देश </W><W> दिए </W><W> गए </W><W> हैं। </W><W> सभी </W><W> स्कूल </W><W> अब </W><W> दो </W><W> जनवरी </W><W> को </W><W> खुलेंगे। </W><W> आंचलिक </W><W> मौसम </W><W> विज्ञान </W><W> केंद्र </W><W> के </W><W> मौसम </W><W> विज्ञानियों </W><W> ने </W><W> बताया </W><W> कि </W><W> आने </W><W> वाले </W><W> दिनों </W><W> में </W><W> मौसम </W><W> से </W><W> राहत </W><W> के </W><W> आसार </W><W> नहीं </W><W> है। </W><AFTER_EFFECTS-ARG ID="51"><LINK EVENT_ARG="48" ID="57" TYPE_REL="EVENT_ARG"/><W> अधिकतम </W><W> पारा </W><W> भी </W><W> पूरे </W><W> प्रदेश </W><W> में </W><W> सामान्य </W><W> से </W><W> 5 </W><W> से </W><W> 12 </W><W> डिग्री </W><W> तक </W><W> कम </W><W> दर्ज </W></AFTER_EFFECTS-ARG><W> हो </W><W> रहा </W><W> है। </W><W> इससे </W><W> गलन </W><W> जारी </W><W> रहेगी, </W><W> दोपहर </W><W> तक </W><W> धूप </W><W> खिलने </W><W> की </W><W> संभावना </W><W> है। </W><W> कोहरा </W><W> अभी </W><W> आने </W><W> वाले </W><W> दिनों </W><W> में </W><W> भी </W><W> छाया </W><W> रहेगा। </W></P></DOCUMENT>