<?xml version="1.0" encoding="UTF-8"?>
<DOCUMENT><DESC/><TIME>2978</TIME><P><PLACE-ARG ID="27"><LINK EVENT_ARG="0" ID="28" TYPE_REL="EVENT_ARG"/><W> असमः </W></PLACE-ARG><W> भीषण </W><NATURAL_EVENT ID="0" TYPE="FLOODS"><W> बाढ़ </W></NATURAL_EVENT><W> से </W><CASUALTIES-ARG ID="1"><LINK EVENT_ARG="0" ID="14" TYPE_REL="EVENT_ARG"/><W> 44 </W><W> की </W><W> मौत, </W></CASUALTIES-ARG><CASUALTIES-ARG ID="2"><LINK EVENT_ARG="0" ID="15" TYPE_REL="EVENT_ARG"/><W> 17 </W><W> लाख </W><W> से </W><W> ज्यादा </W><W> प्रभावित </W></CASUALTIES-ARG><W> । </W></P><P><W> नई </W><W> दिल्ली। </W><PLACE-ARG ID="5"><LINK EVENT_ARG="6" ID="16" TYPE_REL="EVENT_ARG"/><W> असम </W></PLACE-ARG><W> में </W><NATURAL_EVENT ID="6" TYPE="FLOODS"><EVENT-COREF-LINK EVENT_ID="0" ID="24" TYPE_REL="EVENT_COREF"/><W> बाढ़ </W></NATURAL_EVENT><W> से </W><W> स्थिति </W><W> और </W><W> भयावह </W><W> हो </W><W> गई </W><W> है। </W><PLACE-ARG ID="7"><LINK EVENT_ARG="6" ID="17" TYPE_REL="EVENT_ARG"/><W> राज्य </W><W> के </W><W> 24 </W><W> जिले </W></PLACE-ARG><W> बाढ़ </W><W> की </W><W> चपेट </W><W> में </W><W> है। </W><W> अभी </W><W> तक </W><CASUALTIES-ARG ID="3"><LINK EVENT_ARG="6" ID="18" TYPE_REL="EVENT_ARG"/><W> 44 </W><W> लोगों </W><W> की </W><W> जान </W><W> जा </W><W> चुकी </W></CASUALTIES-ARG><W> है। </W><W> करीब </W><CASUALTIES-ARG ID="4"><LINK EVENT_ARG="6" ID="19" TYPE_REL="EVENT_ARG"/><W> 17.2 </W><W> लाख </W><W> लोग </W><W> बाढ़ </W><W> से </W><W> प्रभावित </W></CASUALTIES-ARG><W> हैं। </W><NATURAL_EVENT ID="8" TYPE="FLOODS"><EVENT-COREF-LINK EVENT_ID="0" ID="25" TYPE_REL="EVENT_COREF"/><W> बाढ़ </W></NATURAL_EVENT><W> का </W><W> असर </W><W> इंसानों </W><W> के </W><W> साथ-साथ </W><W> जानवरों </W><W> पर </W><W> पड़ </W><W> रहा </W><W> है। </W><W> गैंडों </W><W> के </W><W> लिए </W><W> मशहूर </W><CASUALTIES-ARG ID="9"><LINK EVENT_ARG="8" ID="20" TYPE_REL="EVENT_ARG"/><W> काजीरंगा </W><W> नैशनल </W><W> पार्क </W><W> आधा </W><W> डूब </W><W> चुका </W></CASUALTIES-ARG><W> है। </W><W> पार्क </W><W> के </W><W> जानवरों </W><W> को </W><W> बाढ़ </W><W> से </W><W> बचाने </W><W> की </W><W> कोशिश </W><W> जारी </W><W> है। </W></P><P><W> प्रधानमंत्री </W><W> नरेंद्र </W><W> मोदी </W><W> ने </W><W> पूर्वोत्तर </W><W> के </W><W> विभिन्न </W><W> हिस्से </W><W> में </W><W> बाढ़ </W><W> की </W><W> स्थिति </W><W> पर </W><W> पीड़ा </W><W> का </W><W> इजहार </W><W> किया </W><W> है। </W><W> उन्होंने </W><W> इससे </W><W> निपटने </W><W> के </W><W> लिए </W><W> केंद्र </W><W> से </W><W> सभी </W><W> तरह </W><W> की </W><W> सहायता </W><W> देने </W><W> का </W><W> वादा </W><W> किया </W><W> है। </W><W> साथ </W><W> ही </W><W> गृह </W><W> राज्य </W><W> मंत्री </W><W> किरण </W><W> रिजिजू </W><W> से </W><W> बचाव </W><W> एवं </W><W> राहत </W><W> कार्यों </W><W> के </W><W> पर्यवेक्षण </W><W> और </W><W> सभी </W><W> जरूरी </W><W> मदद </W><W> उपलब्ध </W><W> कराने </W><W> को </W><W> कहा </W><W> है। </W></P><P><W> प्रधानमंत्री </W><W> ने </W><W> बाढ़ </W><W> की </W><W> स्थिति </W><W> को </W><W> लेकर </W><W> अरुणाचल </W><W> प्रदेश </W><W> के </W><W> मुख्यमंत्री </W><W> पेमा </W><W> खांडू </W><W> और </W><W> असम </W><W> के </W><W> मुख्यमंत्री </W><W> सर्बानंद </W><W> सोनोवाल </W><W> से </W><W> बातचीत </W><W> की </W><W> है। </W><W> इसके </W><W> अलावा </W><W> उन्होंने </W><W> वीडियो </W><W> कांफ्रेंसिंग </W><W> के </W><W> जरिये </W><W> राज्यों </W><W> के </W><W> शीर्ष </W><W> अधिकारियों </W><W> के </W><W> साथ </W><W> हर </W><W> महीने </W><W> होने </W><W> वाली </W><W> 'प्रगति' </W><W> बैठक </W><W> में </W><W> भी </W><W> पूर्वाेत्तर </W><W> बाढ़ </W><W> की </W><W> स्थिति </W><W> की </W><W> समीक्षा </W><W> की। </W><W> प्रधानमंत्री </W><W> ने </W><W> ट्वीट </W><W> कर </W><W> कहा, </W><W> 'पूर्वोत्तर </W><W> के </W><W> विभिन्न </W><W> हिस्सों </W><W> में </W><W> बाढ़ </W><W> प्रभावित </W><W> लोगों </W><W> की </W><W> पीड़ा </W><W> को </W><W> साझा </W><W> करता </W><W> हूं। </W></P><P><W> असम </W><W> के </W><W> मुख्यमंत्री </W><W> सर्वानंद </W><W> सोनोवाल </W><W> ने </W><W> बुधवार </W><W> को </W><W> बाढ़ग्रस्त </W><W> माजुली </W><W> जिले </W><W> का </W><W> दौरा </W><W> किया </W><W> और </W><W> राहत </W><W> शिविरों </W><W> का </W><W> जायजा </W><W> लिया। </W><W> भीषण </W><NATURAL_EVENT ID="10" TYPE="FLOODS"><EVENT-COREF-LINK EVENT_ID="0" ID="23" TYPE_REL="EVENT_COREF"/><W> बाढ़ </W></NATURAL_EVENT><W> के </W><W> चलते </W><AFTER_EFFECTS-ARG ID="11"><LINK EVENT_ARG="10" ID="21" TYPE_REL="EVENT_ARG"/><W> 1,760 </W><W> हेक्टेयर </W><W> की </W><W> फसल </W><W> बर्बाद </W></AFTER_EFFECTS-ARG><W> हो </W><W> गई </W><W> है </W><W> और </W><CASUALTIES-ARG ID="12"><LINK EVENT_ARG="10" ID="22" TYPE_REL="EVENT_ARG"/><W> सैकड़ों </W><W> लोग </W><W> बेघर </W></CASUALTIES-ARG><W> हो </W><W> गए </W><W> हैं। </W><W> सोनोवाल </W><W> ने </W><W> काजीरंगा </W><W> अभयारण्य </W><W> का </W><W> भी </W><W> दौरा </W><W> किया </W><W> और </W><W> अधिकारियों </W><W> को </W><W> पशुओं </W><W> पर </W><W> नजर </W><W> रखने </W><W> का </W><W> निर्देश </W><W> दिया, </W><W> ताकि </W><W> वे </W><W> शिकारियों </W><W> का </W><W> निशाना </W><W> न </W><W> बनें। </W><W> उन्होंने </W><W> कहा </W><W> कि </W><W> नगांव, </W><W> गोलाघाट, </W><W> कार्बी </W><W> आंगलोंग, </W><W> सोनितपुर </W><W> जिलों </W><W> का </W><W> प्रशासन </W><NATURAL_EVENT ID="13" TYPE="FLOODS"><EVENT-COREF-LINK EVENT_ID="0" ID="26" TYPE_REL="EVENT_COREF"/><W> बाढ़ </W></NATURAL_EVENT><W> के </W><W> हालात </W><W> के </W><W> बारे </W><W> में </W><W> रोज </W><W> वन </W><W> मंत्री </W><W> को </W><W> रिपोर्ट </W><W> करेगा </W><W> और </W><W> पशुओं </W><W> की </W><W> सुरक्षा </W><W> के </W><W> उपाय </W><W> करेगा। </W></P><P><W> पूर्वोत्तर </W><W> के </W><W> बाढ़ </W><W> प्रभावित </W><W> इलाकों </W><W> में </W><W> राहत </W><W> एवं </W><W> बचाव </W><W> अभियानों </W><W> का </W><W> आकलन </W><W> करने </W><W> के </W><W> लिए </W><W> केंद्रीय </W><W> मंत्री </W><W> किरन </W><W> रिजिजू </W><W> के </W><W> नेतृत्व </W><W> में </W><W> एक </W><W> उच्च </W><W> स्तरीय </W><W> केंद्रीय </W><W> दल </W><W> जाएगा। </W><W> इस </W><W> घड़ी </W><W> में </W><W> पूरा </W><W> देश </W><W> पूर्वोत्तर </W><W> के </W><W> लोगों </W><W> के </W><W> साथ </W><W> है। </W><W> रिजिजू </W><W> के </W><W> नेतृत्व </W><W> में </W><W> उच्चस्तरीय </W><W> केंद्रीय </W><W> दल </W><W> राहत </W><W> एवं </W><W> बचाव </W><W> कार्यों </W><W> का </W><W> जायजा </W><W> लेने </W><W> के </W><W> लिए </W><W> गुरुवार </W><W> से </W><W> तीन </W><W> दिनों </W><W> तक </W><W> असम, </W><W> अरुणाचल </W><W> प्रदेश </W><W> और </W><W> मणिपुर </W><W> का </W><W> दौरा </W><W> करेगा। </W><W> दल </W><W> में </W><W> राष्ट्रीय </W><W> आपदा </W><W> प्रबंधन </W><W> अथारिटी, </W><W> नीति </W><W> आयोग </W><W> और </W><W> एनडीआरएफ </W><W> के </W><W> सदस्य </W><W> शामिल </W><W> हैं। </W></P></DOCUMENT>