<?xml version="1.0" encoding="UTF-8"?>
<DOCUMENT><DESC/><TIME>1728</TIME><P><PLACE-ARG ID="0"><LINK EVENT_ARG="3" ID="24" TYPE_REL="EVENT_ARG"/><W> उत्तरकाशी </W></PLACE-ARG><W> में </W><NATURAL_EVENT ID="3" TYPE="EARTHQUAKE"><W> भूकंप </W><W> के </W><W> झटकों </W></NATURAL_EVENT><W> से </W><W> दहशत </W><W> । </W></P><P><PLACE-ARG ID="1"><LINK EVENT_ARG="4" ID="25" TYPE_REL="EVENT_ARG"/><W> उत्तरकाशी। </W></PLACE-ARG><PLACE-ARG ID="2"><LINK EVENT_ARG="4" ID="26" TYPE_REL="EVENT_ARG"/><W> भारत-चीन </W><W> सीमा </W><W> पर </W><W> स्थित </W><W> उत्तरकाशी </W><W> जिले </W></PLACE-ARG><W> में </W><NATURAL_EVENT ID="4" TYPE="EARTHQUAKE"><EVENT-COREF-LINK EVENT_ID="3" ID="39" TYPE_REL="EVENT_COREF"/><W> भूकंप </W><W> के </W><W> झटके </W></NATURAL_EVENT><W> महसूस </W><W> किए </W><W> गए। </W><NATURAL_EVENT ID="5" TYPE="EARTHQUAKE"><EVENT-COREF-LINK EVENT_ID="3" ID="40" TYPE_REL="EVENT_COREF"/><W> भूकंप </W></NATURAL_EVENT><W> की </W><MAGNITUDE-ARG ID="6"><LINK EVENT_ARG="5" ID="27" TYPE_REL="EVENT_ARG"/><W> तीव्रता </W><W> रिक्टर </W><W> पैमाने </W><W> पर </W><W> 3.5 </W></MAGNITUDE-ARG><W> मापी </W><W> गई </W><W> और </W><W> इसका </W><W> केंद्र </W><EPICENTRE-ARG ID="7"><LINK EVENT_ARG="5" ID="28" TYPE_REL="EVENT_ARG"/><W> जिला </W><W> मुख्यालय </W><W> से </W><W> 15 </W><W> किलोमीटर </W><W> दूर </W><W> डूंडा </W><W> कस्बे </W></EPICENTRE-ARG><W> में </W><W> था। </W><CASUALTIES-ARG ID="8"><LINK EVENT_ARG="5" ID="29" TYPE_REL="EVENT_ARG"/><W> दहशतजदा </W><W> लोग </W><W> घरों </W><W> और </W><W> दुकानों </W><W> से </W><W> बाहर </W><W> निकल </W><W> आए। </W></CASUALTIES-ARG></P><P><W> जिलाधिकारी </W><W> डॉ. </W><W> आशीष </W><W> चौहान </W><W> ने </W><W> तत्काल </W><W> अधिकारियों </W><W> की </W><W> बैठक </W><W> बुलाकर </W><W> हालात </W><W> की </W><W> समीक्षा </W><W> की। </W><W> डीएम </W><W> ने </W><W> बताया </W><W> कि </W><W> कहीं </W><W> से </W><W> जानमाल </W><W> के </W><W> नुकसान </W><W> की </W><W> सूचना </W><W> नहीं </W><W> है। </W><W> इससे </W><W> पहले </W><TIME-ARG ID="9"><LINK EVENT_ARG="10" ID="30" TYPE_REL="EVENT_ARG"/><W> पिछले </W><W> साल </W><W> चार </W><W> दिसंबर </W></TIME-ARG><W> को </W><NATURAL_EVENT ID="10" TYPE="EARTHQUAKE"><EVENT-COREF-LINK EVENT_ID="3" ID="41" TYPE_REL="EVENT_COREF"/><W> भूकंप </W><W> के </W><W> झटके </W></NATURAL_EVENT><W> महसूस </W><W> किए </W><W> गए </W><W> थे। </W><W> इसकी </W><MAGNITUDE-ARG ID="11"><LINK EVENT_ARG="10" ID="31" TYPE_REL="EVENT_ARG"/><W> तीव्रता </W><W> रिक्टर </W><W> पैमान </W><W> पर </W><W> 3.2 </W></MAGNITUDE-ARG><W> मापी </W><W> गई </W><W> थी। </W></P><P><W> आपदा </W><W> प्रबंधन </W><W> अधिकारी </W><W> देवेंद्र </W><W> पटवाल </W><W> के </W><W> अनुसार </W><TIME-ARG ID="12"><LINK EVENT_ARG="13" ID="32" TYPE_REL="EVENT_ARG"/><W> गुरुवार </W><W> सुबह </W></TIME-ARG><W> पहला </W><NATURAL_EVENT ID="13" TYPE="EARTHQUAKE"><EVENT-COREF-LINK EVENT_ID="3" ID="42" TYPE_REL="EVENT_COREF"/><W> झटका </W></NATURAL_EVENT><TIME-ARG ID="14"><LINK EVENT_ARG="15" ID="33" TYPE_REL="EVENT_ARG"/><W> 11:27 </W><W> बजे </W></TIME-ARG><W> महसूस </W><W> किया। </W><W> हालांकि </W><NATURAL_EVENT ID="15" TYPE="EARTHQUAKE"><EVENT-COREF-LINK EVENT_ID="3" ID="43" TYPE_REL="EVENT_COREF"/><W> इसकी </W></NATURAL_EVENT><MAGNITUDE-ARG ID="17"><LINK EVENT_ARG="15" ID="34" TYPE_REL="EVENT_ARG"/><W> तीव्रता </W><W> रिक्टर </W><W> पैमाने </W><W> पर </W><W> 2.8 </W></MAGNITUDE-ARG><W> थी </W><W> और </W><W> केंद्र </W><EPICENTRE-ARG ID="18"><LINK EVENT_ARG="15" ID="35" TYPE_REL="EVENT_ARG"/><W> डूंडा </W></EPICENTRE-ARG><W> में </W><W> ही </W><W> था। </W><W> इसके </W><W> ठीक </W><TIME-ARG ID="19"><LINK EVENT_ARG="20" ID="36" TYPE_REL="EVENT_ARG"/><W> 31 </W><W> मिनट </W><W> बाद </W><W> 11:58 </W><W> बजे </W></TIME-ARG><NATURAL_EVENT ID="20" TYPE="EARTHQUAKE"><EVENT-COREF-LINK EVENT_ID="3" ID="44" TYPE_REL="EVENT_COREF"/><W> दूसरा </W><W> झटका </W></NATURAL_EVENT><W> महसूस </W><W> किया </W><W> गया। </W><NATURAL_EVENT ID="21" TYPE="EARTHQUAKE"><EVENT-COREF-LINK EVENT_ID="3" ID="45" TYPE_REL="EVENT_COREF"/><W> भूकंप </W><W> के </W><W> झटके </W></NATURAL_EVENT><PLACE-ARG ID="22"><LINK EVENT_ARG="21" ID="37" TYPE_REL="EVENT_ARG"/><W> उत्तरकाशी, </W><W> भटवाड़ी, </W><W> जोशियाड़ा, </W><W> ज्ञानसू, </W><W> डुंडा, </W><W> चिन्यालीसौड </W><W> समेत </W><W> अनेक </W><W> क्षेत्रों </W></PLACE-ARG><W> में </W><W> महसूस </W><W> किए </W><W> गए। </W><AFTER_EFFECTS-ARG ID="23"><LINK EVENT_ARG="21" ID="38" TYPE_REL="EVENT_ARG"/><W> भयभीत </W><W> लोग </W><W> घरों </W><W> और </W><W> दुकानों </W><W> से </W><W> बाहर </W><W> निकल </W><W> आए। </W></AFTER_EFFECTS-ARG><W> डीएम </W><W> के </W><W> अनुसार </W><W> अफसरों </W><W> को </W><W> अलर्ट </W><W> रहने </W><W> को </W><W> कहा </W><W> गया </W><W> है। </W></P></DOCUMENT>