<?xml version="1.0" encoding="UTF-8"?>
<DOCUMENT><DESC/><DESC/><DESC/><TIME>18053</TIME><P><NATURAL_EVENT ID="1" TYPE="AVALANCHES"><W> हिमस्खलन </W></NATURAL_EVENT><W> में </W><AFTER_EFFECTS-ARG ID="9"><LINK EVENT_ARG="1" ID="30" TYPE_REL="EVENT_ARG"/><W> सैन्य </W><W> चौकी </W><W> तबाह, </W></AFTER_EFFECTS-ARG><CASUALTIES-ARG ID="10"><LINK EVENT_ARG="1" ID="31" TYPE_REL="EVENT_ARG"/><W> 10 </W><W> जवान </W><W> लापता </W></CASUALTIES-ARG><W> । </W></P><P><W> श्रीनगर। </W><PLACE-ARG ID="11"><LINK EVENT_ARG="2" ID="32" TYPE_REL="EVENT_ARG"/><W> दुनिया </W><W> के </W><W> सबसे </W><W> ऊंचे </W><W> और </W><W> दुर्गम </W><W> युद्ध </W><W> क्षेत्र </W><W> सियाचिन </W><W> ग्लेशियर </W></PLACE-ARG><W> में </W><TIME-ARG ID="12"><LINK EVENT_ARG="2" ID="33" TYPE_REL="EVENT_ARG"/><W> बुधवार </W><W> की </W><W> सुबह </W></TIME-ARG><W> हुए </W><NATURAL_EVENT ID="2" TYPE="AVALANCHES"><EVENT-COREF-LINK EVENT_ID="1" ID="53" TYPE_REL="EVENT_COREF"/><W> हिमस्खलन </W></NATURAL_EVENT><W> में </W><AFTER_EFFECTS-ARG ID="13"><LINK EVENT_ARG="2" ID="34" TYPE_REL="EVENT_ARG"/><W> एक </W><W> सैन्य </W><W> चौकी </W><W> पूरी </W><W> तरह </W><W> तबाह </W></AFTER_EFFECTS-ARG><W> हो </W><W> गई। </W><CASUALTIES-ARG ID="14"><LINK EVENT_ARG="2" ID="35" TYPE_REL="EVENT_ARG"/><W> चौकी </W><W> में </W><W> मौजूद </W><W> 10 </W><W> सैन्यकर्मी </W><W> लापता </W></CASUALTIES-ARG><W> हैं। </W><W> सेना </W><W> और </W><W> वायुसेना </W><W> का </W><W> बचाव </W><W> दल </W><W> अपने </W><W> खोजी </W><W> कुत्तों </W><W> और </W><W> अत्याधुनिक </W><W> उपकरणों </W><W> की </W><W> मदद </W><W> से </W><W> उनका </W><W> पता </W><W> लगाने </W><W> में </W><W> जुटा </W><W> है। </W><W> सभी </W><W> लापता </W><W> जवान </W><W> सेना </W><W> की </W><W> मद्रास </W><W> रेजिमेंट </W><W> से </W><W> संबंधित </W><W> बताए </W><W> जाते </W><W> हैं। </W></P><P><TIME-ARG ID="15"><LINK EVENT_ARG="3" ID="36" TYPE_REL="EVENT_ARG"/><W> बुधवार </W><W> को </W><W> सुबह </W></TIME-ARG><W> में </W><PLACE-ARG ID="16"><LINK EVENT_ARG="3" ID="37" TYPE_REL="EVENT_ARG"/><W> सियाचिन </W><W> ग्लेशियर </W><W> के </W><W> उत्तरी </W><W> छोर </W></PLACE-ARG><W> पर </W><NATURAL_EVENT ID="3" TYPE="BLIZZARD"><W> बर्फीला </W><W> तूफान </W></NATURAL_EVENT><W> आने </W><W> के </W><W> साथ </W><W> ही </W><NATURAL_EVENT ID="4" TYPE="AVALANCHES"><EVENT-COREF-LINK EVENT_ID="1" ID="52" TYPE_REL="EVENT_COREF"/><W> हिमस्खलन </W></NATURAL_EVENT><W> हुआ। </W><NATURAL_EVENT ID="18" TYPE="AVALANCHES"><W> इसमें </W></NATURAL_EVENT><AFTER_EFFECTS-ARG ID="17"><LINK EVENT_ARG="4" ID="38" TYPE_REL="EVENT_ARG"/><W> सेना </W><W> की </W><W> एक </W><W> अग्रिम </W><W> चौकी </W><W> तबाह </W></AFTER_EFFECTS-ARG><W> हो </W><W> गई। </W><CASUALTIES-ARG ID="20"><LINK EVENT_ARG="4" ID="39" TYPE_REL="EVENT_ARG"/><W> चौकी </W><W> और </W><W> उसमें </W><W> मौजूद </W><W> 10 </W><W> सैन्यकर्मी </W><W> कई </W><W> फीट </W><W> बर्फ </W><W> के </W><W> नीचे </W><W> दब </W><W> गए </W></CASUALTIES-ARG><W> हैं। </W><W> रक्षा </W><W> मंत्रालय </W><W> के </W><W> प्रवक्ता </W><W> कर्नल </W><W> एसडी </W><W> गोस्वामी </W><W> ने </W><W> इस </W><W> हादसे </W><W> की </W><W> पुष्टि </W><W> करते </W><W> हुए </W><W> बताया </W><W> कि </W><PLACE-ARG ID="41"><LINK EVENT_ARG="5" ID="42" TYPE_REL="EVENT_ARG"/><W> समुद्रतल </W><W> से </W><W> लगभग </W><W> 20 </W><W> हजार </W><W> फीट </W><W> की </W><W> ऊंचाई </W><W> पर </W><W> स्थित </W><W> सियाचिन </W><W> ग्लेशियर </W></PLACE-ARG><W> में </W><TIME-ARG ID="40"><LINK EVENT_ARG="5" ID="43" TYPE_REL="EVENT_ARG"/><W> सुबह </W><W> करीब </W><W> साढ़े </W><W> सात </W><W> बजे </W></TIME-ARG><NATURAL_EVENT ID="5" TYPE="BLIZZARD"><EVENT-COREF-LINK EVENT_ID="3" ID="54" TYPE_REL="EVENT_COREF"/><W> बर्फीला </W><W> तूफान </W></NATURAL_EVENT><W> आया </W><W> था। </W><W> इसी </W><W> दौरान </W><W> हुए </W><NATURAL_EVENT ID="6" TYPE="AVALANCHES"><EVENT-COREF-LINK EVENT_ID="1" ID="51" TYPE_REL="EVENT_COREF"/><W> हिमस्खलन </W></NATURAL_EVENT><W> में </W><W> एक </W><W> चौकी </W><W> तबाह </W><W> हो </W><W> गई। </W><W> लापता </W><W> जवानों </W><W> के </W><W> मारे </W><W> जाने </W><W> की </W><W> आशंका </W><W> पर </W><W> उन्होंने </W><W> कहा </W><W> कि </W><W> जब </W><W> तक </W><W> हमें </W><W> किसी </W><W> का </W><W> शव </W><W> नहीं </W><W> मिलेगा, </W><W> हम </W><W> उसकी </W><W> मौत </W><W> की </W><W> पुष्टि </W><W> नहीं </W><W> कर </W><W> सकते। </W></P><P><TIME-ARG ID="21"><LINK EVENT_ARG="23" ID="44" TYPE_REL="EVENT_ARG"/><W> बीते </W><W> चार </W><W> माह </W></TIME-ARG><W> के </W><W> दौरान </W><PLACE-ARG ID="22"><LINK EVENT_ARG="23" ID="45" TYPE_REL="EVENT_ARG"/><W> सियाचिन </W></PLACE-ARG><W> में </W><NATURAL_EVENT ID="23" TYPE="AVALANCHES"><W> हिमस्खलन </W></NATURAL_EVENT><W> में </W><W> सैन्यकर्मियों </W><W> के </W><W> मारे </W><W> जाने </W><W> अथवा </W><W> लापता </W><W> होने </W><W> की </W><W> यह </W><W> तीसरी </W><W> घटना </W><W> है। </W><TIME-ARG ID="24"><LINK EVENT_ARG="7" ID="46" TYPE_REL="EVENT_ARG"/><W> 13 </W><W> नवंबर, </W><W> 2015 </W></TIME-ARG><W> को </W><PLACE-ARG ID="25"><LINK EVENT_ARG="7" ID="47" TYPE_REL="EVENT_ARG"/><W> सियाचिन </W><W> ग्लेशियर </W><W> के </W><W> दक्षिणी </W><W> छोर </W><W> पर </W></PLACE-ARG><W> हुए </W><NATURAL_EVENT ID="7" TYPE="AVALANCHES"><W> हिमस्खलन </W></NATURAL_EVENT><W> में </W><W> सेना </W><W> की </W><CASUALTIES-ARG ID="26"><LINK EVENT_ARG="7" ID="48" TYPE_REL="EVENT_ARG"/><W> 3 </W><W> स्काउट्स </W><W> के </W><W> एक </W><W> कैप्टन </W><W> अश्वनी </W><W> कुमार </W><W> शहीद </W><W> हो </W><W> गए </W></CASUALTIES-ARG><W> थे, </W><W> जबकि </W><W> 15 </W><W> जवानों </W><W> को </W><W> बाद </W><W> में </W><W> बचाव </W><W> दल </W><W> ने </W><W> बचा </W><W> लिया </W><W> था। </W><W> इसके </W><W> बाद </W><W> इसी </W><W> इलाके </W><W> में </W><TIME-ARG ID="28"><LINK EVENT_ARG="8" ID="49" TYPE_REL="EVENT_ARG"/><W> तीन </W><W> जनवरी, </W><W> 2016 </W></TIME-ARG><W> को </W><W> हुए </W><NATURAL_EVENT ID="8" TYPE="AVALANCHES"><W> हिमस्खलन </W></NATURAL_EVENT><W> में </W><CASUALTIES-ARG ID="29"><LINK EVENT_ARG="8" ID="50" TYPE_REL="EVENT_ARG"/><W> 3 </W><W> स्काउट्स </W><W> से </W><W> संबंधित </W><W> चार </W><W> जवान </W><W> शहीद </W><W> हो </W><W> गए </W></CASUALTIES-ARG><W> थे। </W></P></DOCUMENT>