<?xml version="1.0" encoding="UTF-8"?>
<DOCUMENT><P><W> भोपाल। </W><PLACE-ARG ID="3"><LINK EVENT_ARG="0" ID="12" TYPE_REL="EVENT_ARG"/><W> भोपाल-इंदौर </W><W> रोड </W><W> स्थित </W><W> भौंरी </W></PLACE-ARG><W> में </W><W> एक </W><PLACE-ARG ID="4"><LINK EVENT_ARG="0" ID="11" TYPE_REL="EVENT_ARG"/><W> आयल </W><W> पेंट </W><W> की </W><W> फैक्टरी </W></PLACE-ARG><W> में </W><TIME-ARG ID="2"><LINK EVENT_ARG="0" ID="10" TYPE_REL="EVENT_ARG"/><W> आज </W><W> सुबह </W></TIME-ARG><MAN_MADE_EVENT ID="0" TYPE="INDUSTRIAL_ACCIDENT"><W> आग </W><W> लग </W><W> गई। </W></MAN_MADE_EVENT><W> इससे </W><CASUALTIES-ARG ID="8"><LINK EVENT_ARG="0" ID="13" TYPE_REL="EVENT_ARG"/><W> लाखों </W><W> रुपए </W><W> का </W><W> नुकसान </W><W> हो </W><W> गया </W></CASUALTIES-ARG><W> जिस </W><W> पर </W><W> काबू </W><W> पाने </W><W> के </W><W> लिए </W><W> नगर </W><W> निगम </W><W> की </W><W> दमकलें </W><W> पहुंची। </W></P><P><W> जानकारी </W><W> के </W><W> मुताबिक </W><PLACE-ARG ID="5"><LINK EVENT_ARG="1" ID="16" TYPE_REL="EVENT_ARG"/><W> भौंरी </W><W> स्थित </W><W> आयल </W><W> पेंट </W></PLACE-ARG><W> की </W><PLACE-ARG ID="6"><LINK EVENT_ARG="1" ID="15" TYPE_REL="EVENT_ARG"/><W> फैक्टरी </W><W> शिवा </W><W> इंटरप्राइजेज </W></PLACE-ARG><W> में </W><TIME-ARG ID="7"><LINK EVENT_ARG="1" ID="14" TYPE_REL="EVENT_ARG"/><W> आज </W><W> सुबह </W></TIME-ARG><W> अचानक </W><MAN_MADE_EVENT ID="1" TYPE="INDUSTRIAL_ACCIDENT"><EVENT-COREF-LINK EVENT_ID="0" ID="18" TYPE_REL="EVENT_COREF"/><W> आग </W><W> लग </W><W> गई। </W></MAN_MADE_EVENT><W> आग </W><W> इतनी </W><W> भीषण </W><W> थी </W><W> कि </W><W> आसपास </W><W> करीब </W><W> एक </W><W> किलोमीटर </W><W> क्षेत्र </W><W> के </W><W> आसमान </W><W> में </W><W> काला </W><W> धुंआ </W><W> छा </W><W> गया। </W><W> नगर </W><W> निगम </W><W> की </W><W> करीब </W><W> दो </W><W> दर्जन </W><W> दमकलों </W><W> को </W><W> आग </W><W> पर </W><W> काबू </W><W> पाने </W><W> के </W><W> लिए </W><W> भेजा </W><W> गया </W><W> लेकिन </W><W> तब </W><W> तक </W><CASUALTIES-ARG ID="9"><LINK EVENT_ARG="1" ID="17" TYPE_REL="EVENT_ARG"/><W> लाखों </W><W> रुपए </W><W> का </W><W> आयल </W><W> पेंट </W><W> और </W><W> अन्य </W><W> सामग्री </W><W> जल </W><W> गई </W><W> थी। </W></CASUALTIES-ARG><W> आग </W><W> पर </W><W> काबू </W><W> करने </W><W> की </W><W> कोशिशें </W><W> जारी </W><W> हैं। </W></P></DOCUMENT>