<?xml version="1.0" encoding="UTF-8"?>
<DOCUMENT><DESC/><TIME>348</TIME><P><REASON-ARG ID="0"><LINK EVENT_ARG="2" ID="23" TYPE_REL="EVENT_ARG"/><W> पायलट </W><W> की </W><W> सेल्फी </W></REASON-ARG><W> से </W><MAN_MADE_EVENT ID="2" TYPE="AVIATION_HAZARD"><W> क्रेश </W><W> हुआ </W><W> था </W><W> विमान </W></MAN_MADE_EVENT></P><P><W> एक </W><W> अमेरिकी </W><W> विमान </W><W> के </W><W> पायलट </W><W> का </W><W> कॉकपिट </W><W> में </W><W> सेल्फी </W><W> लेना </W><W> भारी </W><W> पड़ </W><W> गया। </W><W> अमेरिकी </W><W> जांचकर्ताओं </W><W> का </W><W> कहना </W><W> है </W><W> कि </W><W> जिस </W><W> वक्त </W><REASON-ARG ID="3"><LINK EVENT_ARG="4" ID="24" TYPE_REL="EVENT_ARG"/><W> पायलट </W><W> सेल्फी </W><W> खींचने </W><W> में </W><W> मशगूल </W><W> था </W></REASON-ARG><W> उसी </W><W> वक्त </W><W> विमान </W><W> अपने </W><W> तय </W><W> मार्ग </W><W> से </W><W> भटककर </W><MAN_MADE_EVENT ID="4" TYPE="AVIATION_HAZARD"><EVENT-COREF-LINK EVENT_ID="2" ID="18" TYPE_REL="EVENT_COREF"/><W> दुर्घटना </W><W> का </W><W> शिकार </W></MAN_MADE_EVENT><W> हो </W><W> गया। </W><TIME-ARG ID="5"><LINK EVENT_ARG="6" ID="25" TYPE_REL="EVENT_ARG"/><W> पिछले </W><W> साल </W><W> 31 </W><W> मई </W></TIME-ARG><W> को </W><W> हुए </W><W> इस </W><MAN_MADE_EVENT ID="6" TYPE="AVIATION_HAZARD"><EVENT-COREF-LINK EVENT_ID="2" ID="19" TYPE_REL="EVENT_COREF"/><W> हादसे </W></MAN_MADE_EVENT><W> के </W><W> कारणों </W><W> का </W><W> अब </W><W> जाकर </W><W> पता </W><W> लगा </W><W> है।इस </W><MAN_MADE_EVENT ID="7" TYPE="AVIATION_HAZARD"><EVENT-COREF-LINK EVENT_ID="2" ID="20" TYPE_REL="EVENT_COREF"/><W> विमान </W><W> दुर्घटना </W></MAN_MADE_EVENT><W> में </W><W> 29 </W><W> वर्षीय </W><CASUALTIES-ARG ID="8"><LINK EVENT_ARG="7" ID="26" TYPE_REL="EVENT_ARG"/><W> पायलट </W><W> समेत </W><W> उन </W><W> तमाम </W><W> यात्रियों </W><W> की </W><W> मौत </W><W> हो </W><W> गई </W><W> थी </W><W> जो </W><W> उस </W><W> वक्त </W><W> उसमें </W><W> सवार </W><W> थे। </W></CASUALTIES-ARG><W> मार्ग </W><W> भटकने </W><W> के </W><W> बाद </W><PARTICIPANT-ARG ID="9"><LINK EVENT_ARG="11" ID="27" TYPE_REL="EVENT_ARG"/><W> सेसना </W><W> 150के </W></PARTICIPANT-ARG><W> नामक </W><W> यह </W><W> विमान </W><PLACE-ARG ID="10"><LINK EVENT_ARG="11" ID="28" TYPE_REL="EVENT_ARG"/><W> अमेरिका </W><W> के </W><W> कालरेडो </W><W> प्रांत </W><W> में </W><W> एक </W><W> खेत </W></PLACE-ARG><W> में </W><W> जाकर </W><MAN_MADE_EVENT ID="11" TYPE="AVIATION_HAZARD"><EVENT-COREF-LINK EVENT_ID="2" ID="21" TYPE_REL="EVENT_COREF"/><W> गिर </W><W> गया </W></MAN_MADE_EVENT><W> था।नेशनल </W><W> ट्रांसपोर्टेशन </W><W> सेफ्टी </W><W> बोर्ड </W><W> ने </W><W> कॉकपिट </W><W> में </W><W> दर्ज </W><W> हुए </W><W> वीडियो </W><W> का </W><W> सहारा </W><W> लेते </W><W> हुए </W><TIME-ARG ID="12"><LINK EVENT_ARG="14" ID="29" TYPE_REL="EVENT_ARG"/><W> बीते </W><W> मंगलवार </W></TIME-ARG><W> को </W><W> यह </W><W> अनुमान </W><W> लगाया </W><W> कि </W><REASON-ARG ID="13"><LINK EVENT_ARG="14" ID="30" TYPE_REL="EVENT_ARG"/><W> पायलट </W><W> के </W><W> सेल्फी </W><W> लेने </W><W> के </W></REASON-ARG><W> चक्कर </W><W> में </W><W> ही </W><W> विमान </W><MAN_MADE_EVENT ID="14" TYPE="AVIATION_HAZARD"><EVENT-COREF-LINK EVENT_ID="2" ID="22" TYPE_REL="EVENT_COREF"/><W> दुर्घटना </W></MAN_MADE_EVENT><W> का </W><W> शिकार </W><W> हुआ।सेलफोन </W><W> के </W><W> इस्तेमाल </W><W> वाले </W><W> साक्ष्य </W><W> को </W><W> आधार </W><W> मानते </W><W> हुए </W><W> यह </W><W> अनुमान </W><W> लगाया </W><W> गया </W><W> है </W><W> कि </W><REASON-ARG ID="15"><LINK EVENT_ARG="16" ID="31" TYPE_REL="EVENT_ARG"/><W> उड़ान </W><W> के </W><W> दौरान </W><W> ही </W><W> सेलफोन </W><W> के </W><W> इस्तेमाल </W></REASON-ARG><W> करने </W><W> से </W><W> ही </W><W> विमान </W><W> अपने </W><W> मार्ग </W><W> से </W><W> भटक </W><W> गया </W><W> जिसने </W><W> इस </W><W> बड़ी </W><MAN_MADE_EVENT ID="16" TYPE="AVIATION_HAZARD"><EVENT-COREF-LINK EVENT_ID="2" ID="17" TYPE_REL="EVENT_COREF"/><W> दु्र्घटना </W></MAN_MADE_EVENT><W> को </W><W> अंजाम </W><W> दिया।(साभार: </W><W> एचटी) </W></P></DOCUMENT>