<?xml version="1.0" encoding="UTF-8"?>
<DOCUMENT><DESC/><DESC/><TIME>2689</TIME><P><PLACE-ARG ID="0"><LINK EVENT_ARG="5" ID="16" TYPE_REL="EVENT_ARG"/><W> इंडोनेशिया </W></PLACE-ARG><W> में </W><MAGNITUDE-ARG ID="3"><LINK EVENT_ARG="5" ID="17" TYPE_REL="EVENT_ARG"/><W> 6.2 </W><W> तीव्रता </W></MAGNITUDE-ARG><W> का </W><NATURAL_EVENT ID="5" TYPE="EARTHQUAKE"><W> भूकंप। </W></NATURAL_EVENT></P><P><W> जकार्ता। </W><PLACE-ARG ID="1"><LINK EVENT_ARG="6" ID="18" TYPE_REL="EVENT_ARG"/><W> इंडोनेशिया </W><W> के </W><W> सुमात्रा </W><W> द्वीप </W></PLACE-ARG><W> पर </W><TIME-ARG ID="14"><LINK EVENT_ARG="6" ID="19" TYPE_REL="EVENT_ARG"/><W> रविवार </W></TIME-ARG><W> को </W><NATURAL_EVENT ID="6" TYPE="EARTHQUAKE"><EVENT-COREF-LINK EVENT_ID="5" ID="26" TYPE_REL="EVENT_COREF"/><W> भूकंप </W><W> के </W><W> झटके </W></NATURAL_EVENT><W> महसूस </W><W> किए </W><W> गए। </W><W> रिक्‍टर </W><W> पैमाने </W><W> पर </W><NATURAL_EVENT ID="7" TYPE="EARTHQUAKE"><EVENT-COREF-LINK EVENT_ID="5" ID="27" TYPE_REL="EVENT_COREF"/><W> इसकी </W></NATURAL_EVENT><MAGNITUDE-ARG ID="4"><LINK EVENT_ARG="7" ID="20" TYPE_REL="EVENT_ARG"/><W> तीव्रता </W><W> 6.2 </W></MAGNITUDE-ARG><W> मापी </W><W> गई </W><W> है। </W><W> हालांकि </W><NATURAL_EVENT ID="8" TYPE="EARTHQUAKE"><EVENT-COREF-LINK EVENT_ID="5" ID="28" TYPE_REL="EVENT_COREF"/><W> भूकंप </W></NATURAL_EVENT><W> के </W><W> बाद </W><W> विशेषज्ञों </W><W> ने </W><W> सुनामी </W><W> की </W><W> चेतावनी </W><W> जारी </W><W> नहीं </W><W> की </W><W> है। </W></P><P><W> जानकारी </W><W> के </W><W> अनुसार </W><NATURAL_EVENT ID="9" TYPE="EARTHQUAKE"><EVENT-COREF-LINK EVENT_ID="5" ID="29" TYPE_REL="EVENT_COREF"/><W> भूकंप </W></NATURAL_EVENT><W> का </W><W> केंद्र </W><EPICENTRE-ARG ID="15"><LINK EVENT_ARG="9" ID="21" TYPE_REL="EVENT_ARG"/><W> तटीय </W><W> बांडा </W><W> एच </W><W> इलाके </W><W> के </W><W> 300 </W><W> किमी </W><W> पश्‍िचम </W><W> में </W><W> 9 </W><W> किमी </W><W> की </W><W> गहराई </W><W> पर </W><W> स्थित </W></EPICENTRE-ARG><W> था। </W><W> भूगर्भ </W><W> विज्ञानियों </W><W> ने </W><W> कहा </W><W> कि </W><W> यह </W><NATURAL_EVENT ID="10" TYPE="EARTHQUAKE"><EVENT-COREF-LINK EVENT_ID="5" ID="30" TYPE_REL="EVENT_COREF"/><W> भूकंप </W></NATURAL_EVENT><W> समुद्र </W><W> के </W><W> अंदर </W><W> आया </W><W> है। </W><W> लेकिन </W><W> इससे </W><W> सुनामी </W><W> का </W><W> कोई </W><W> खतरा </W><W> नहीं </W><W> है। </W></P><P><PLACE-ARG ID="23"><LINK EVENT_ARG="11" ID="24" TYPE_REL="EVENT_ARG"/><W> बांडा </W><W> एच </W><W> इलाके </W></PLACE-ARG><W> में </W><W> आए </W><W> इस </W><NATURAL_EVENT ID="11" TYPE="EARTHQUAKE"><EVENT-COREF-LINK EVENT_ID="5" ID="25" TYPE_REL="EVENT_COREF"/><W> भूकंप </W><W> के </W><W> झटके </W></NATURAL_EVENT><W> पूरे </W><W> प्रांत </W><W> में </W><W> महसूस </W><W> किए </W><W> गए। </W><NATURAL_EVENT ID="13" TYPE="EARTHQUAKE"><EVENT-COREF-LINK EVENT_ID="5" ID="31" TYPE_REL="EVENT_COREF"/><W> इससे </W></NATURAL_EVENT><AFTER_EFFECTS-ARG ID="12"><LINK EVENT_ARG="11" ID="22" TYPE_REL="EVENT_ARG"/><W> लोगों </W><W> में </W><W> कुछ </W><W> देर </W><W> के </W><W> लिए </W><W> दहशत </W><W> भी </W><W> फैल </W><W> गई। </W></AFTER_EFFECTS-ARG><W> हालांकि </W><W> प्रशासन </W><W> के </W><W> अधिकारियों </W><W> ने </W><W> बताया </W><W> है </W><W> कि </W><W> इससे </W><W> किसी </W><W> तरह </W><W> के </W><W> नुकसान </W><W> की </W><W> कोई </W><W> खबर </W><W> नहीं </W><W> है। </W></P></DOCUMENT>